{
  "Génesis": "libros/1_Gn_RVR60.json",
  "Éxodo": "libros/2_Ex_RVR60.json",
  "Levítico": "libros/3_Lv_RVR60.json",
  "Números": "libros/4_Nm_RVR60.json",
  "Deuteronomio": "libros/5_Dt_RVR60.json",
  "Josué": "libros/6_Jos_RVR60.json",
  "Jueces": "libros/7_Jue_RVR60.json",
  "Rut": "libros/8_Rt_RVR60.json",
  "1 Samuel": "libros/9_1S_RVR60.json",
  "2 Samuel": "libros/10_2S_RVR60.json",
  "1 Reyes": "libros/11_1R_RVR60.json",
  "2 Reyes": "libros/12_2R_RVR60.json",
  "1 Crónicas": "libros/13_1C_RVR60.json",
  "2 Crónicas": "libros/14_2C_RVR60.json",
  "Esdras": "libros/15_Esd_RVR60.json",
  "Nehemías": "libros/16_Neh_RVR60.json",
  "Ester": "libros/17_Est_RVR60.json",
  "Job": "libros/18_Job_RVR60.json",
  "Salmos": "libros/19_Sal_RVR60.json",
  "Proverbios": "libros/20_Pr_RVR60.json",
  "Eclesiastés": "libros/21_Ec_RVR60.json",
  "Cantares": "libros/22_Cnt_RVR60.json",
  "Isaías": "libros/23_Is_RVR60.json",
  "Jeremías": "libros/24_Jer_RVR60.json",
  "Lamentaciones": "libros/25_Lm_RVR60.json",
  "Ezequiel": "libros/26_Ez_RVR60.json",
  "Daniel": "libros/27_Dan_RVR60.json",
  "Oseas": "libros/28_Os_RVR60.json",
  "Joel": "libros/29_Jl_RVR60.json",
  "Amós": "libros/30_Am_RVR60.json",
  "Abdías": "libros/31_Abd_RVR60.json",
  "Jonás": "libros/32_Jon_RVR60.json",
  "Miqueas": "libros/33_Mi_RVR60.json",
  "Nahúm": "libros/34_Nah_RVR60.json",
  "Habacuc": "libros/35_Hab_RVR60.json",
  "Sofonías": "libros/36_Sof_RVR60.json",
  "Hageo": "libros/37_Hag_RVR60.json",
  "Zacarías": "libros/38_Zac_RVR60.json",
  "Malaquías": "libros/39_Mal_RVR60.json",
  "Mateo": "libros/40_Mt_RVR60.json",
  "Marcos": "libros/41_Mr_RVR60.json",
  "Lucas": "libros/42_Lc_RVR60.json",
  "Juan": "libros/43_Jn_RVR60.json",
  "Hechos": "libros/44_Ac_RVR60.json",
  "Romanos": "libros/45_Rom_RVR60.json",
  "1 Corintios": "libros/46_1Cor_RVR60.json",
  "2 Corintios": "libros/47_2Cor_RVR60.json",
  "Gálatas": "libros/48_Ga_RVR60.json",
  "Efesios": "libros/49_Ef_RVR60.json",
  "Filipenses": "libros/50_Fil_RVR60.json",
  "Colosenses": "libros/51_Col_RVR60.json",
  "1 Tesalonicenses": "libros/52_1Ts_RVR60.json",
  "2 Tesalonicenses": "libros/53_2Ts_RVR60.json",
  "1 Timoteo": "libros/54_1Tim_RVR60.json",
  "2 Timoteo": "libros/55_2Tim_RVR60.json",
  "Tito": "libros/56_Tit_RVR60.json",
  "Filemón": "libros/57_Flm_RVR60.json",
  "Hebreos": "libros/58_Heb_RVR60.json",
  "Santiago": "libros/59_Jac_RVR60.json",
  "1 Pedro": "libros/60_1P_RVR60.json",
  "2 Pedro": "libros/61_2P_RVR60.json",
  "1 Juan": "libros/62_1Jn_RVR60.json",
  "2 Juan": "libros/63_2Jn_RVR60.json",
  "3 Juan": "libros/64_3Jn_RVR60.json",
  "Judas": "libros/65_Jud_RVR60.json",
  "Apocalipsis" : "libros/66_Rev_RVR60.json"
}